{
  "project_id": "project-contractor_router_probe_20260415t134351z-20260415T134351Z-2c8dd54d",
  "status": "active",
  "created_at": "2026-04-15T13:43:51.114528+00:00",
  "project_name": "Contractor Router Probe 20260415T134351Z",
  "project_type": "Kitchen Remodel",
  "project_description": "Probe-created project for contractor router verification.",
  "client": {
    "name": "Router Probe Client",
    "contact": "router-probe-client@example.com"
  },
  "pm": {
    "name": "Router Probe PM",
    "contact": "router-probe-pm@example.com"
  },
  "site_address": "741 Router Lane, Scottsburg, IN",
  "portfolio_id": "portfolio-router-probe",
  "jurisdiction": {
    "jurisdiction_id": "scottsburg-in",
    "authority_name": "Scottsburg Building Department",
    "city": "Scottsburg",
    "county": "Scott",
    "state": "IN"
  },
  "baseline_refs": {
    "schedule_baseline_id": "schedule-baseline-20260415T134351Z",
    "budget_baseline_id": "budget-baseline-20260415T134351Z",
    "compliance_snapshot_id": "compliance-snapshot-20260415T134351Z",
    "oracle_snapshot_id": "",
    "exposure_profile_id": ""
  },
  "notes": "Generated by stage_contractor_router_probe.py",
  "integrity": {
    "entry_hash": "c16a87cb1c1d87a85a365074f5f288781631127263b8fcdd20fea150a305b46a",
    "linked_receipts": []
  }
}